source_cart/__init__.py
source_cart/run.py
source_cart/schemas/addresses.json
source_cart/schemas/customers_cart.json
source_cart/schemas/order_items.json
source_cart/schemas/order_payments.json
source_cart/schemas/order_statuses.json
source_cart/schemas/orders.json
source_cart/schemas/products.json
source_cart/source.py
source_cart/spec.json
source_cart/streams.py
airbyte_source_cart-0.3.41.dist-info/METADATA
airbyte_source_cart-0.3.41.dist-info/WHEEL
airbyte_source_cart-0.3.41.dist-info/entry_points.txt
airbyte_source_cart-0.3.41.dist-info/RECORD
